Metadata-Version: 1.1
Name: promus
Version: 0.1.2
Summary: Remote manager to handle git commands.
Home-page: http://promus.readthedocs.org
Author: Manuel Lopez
Author-email: jmlopez.rod@gmail.com
License: BSD License
Keywords: ssh git transfer files collaborate access
Platform: Darwin
Platform: Linux
Classifier: Development Status :: 5 - Production/Stable
Classifier: License :: OSI Approved :: BSD License
Classifier: Operating System :: MacOS :: MacOS X
Classifier: Operating System :: POSIX :: Linux
Classifier: Programming Language :: Python
Classifier: Programming Language :: Python :: 2.7
Classifier: Topic :: Communications :: File Sharing
Classifier: Topic :: Software Development :: Version Control
